zope.cachedescriptors-5.0-py3.9-nspkg.pth
zope/cachedescriptors/__init__.py
zope/cachedescriptors/method.py
zope/cachedescriptors/method.rst
zope/cachedescriptors/property.py
zope/cachedescriptors/property.rst
zope/cachedescriptors/tests.py
zope.cachedescriptors-5.0.dist-info/LICENSE.txt
zope.cachedescriptors-5.0.dist-info/METADATA
zope.cachedescriptors-5.0.dist-info/WHEEL
zope.cachedescriptors-5.0.dist-info/namespace_packages.txt
zope.cachedescriptors-5.0.dist-info/top_level.txt
zope.cachedescriptors-5.0.dist-info/RECORD
